cbeams/__init__.py
cbeams/__main__.py
cbeams/animate.py
cbeams/cmdline.py
cbeams/shape.py
cbeams/terminal.py
cbeams-1.0.3.dist-info/LICENSE
cbeams-1.0.3.dist-info/METADATA
cbeams-1.0.3.dist-info/WHEEL
cbeams-1.0.3.dist-info/entry_points.txt
cbeams-1.0.3.dist-info/top_level.txt
cbeams-1.0.3.dist-info/zip-safe
cbeams-1.0.3.dist-info/RECORD
