Metadata-Version: 2.1
Name: cbeams
Version: 1.0.3
Summary: A command-line program which draws pretty animated colored circles in the terminal.
Home-page: http://pypi.python.org/pypi/cbeams/
Author: Jonathan Hartley
Author-email: tartley@tartley.com
License: UNKNOWN
Keywords: console blessings ansi terminal animation
Platform: UNKNOWN
Classifier: Development Status :: 4 - Beta
Classifier: Environment :: Console
Classifier: Intended Audience :: Developers
Classifier: License :: OSI Approved :: BSD License
Classifier: Natural Language :: English
Classifier: Operating System :: POSIX :: Linux
Classifier: Operating System :: OS Independent
Classifier: Programming Language :: Python :: 3
Classifier: Programming Language :: Python :: 3.4
Classifier: Programming Language :: Python :: 3.5
Classifier: Programming Language :: Python :: Implementation :: CPython
Classifier: Topic :: Games/Entertainment
Requires-Dist: blessings (>=1.6)
Requires-Dist: docopt (>=0.6.1)
